minsketch/__init__.py
minsketch/count_mean_sketch.py
minsketch/count_min_sketch.py
minsketch/counter_sketch_hybrid.py
minsketch/double_hashing.py
minsketch/hash_strategy.py
minsketch/heap.py
minsketch/least_squares_sketch.py
minsketch/lossy_strategy.py
minsketch/sketch_tables.py
minsketch/update_strategy.py
minsketch-0.1.dist-info/DESCRIPTION.rst
minsketch-0.1.dist-info/METADATA
minsketch-0.1.dist-info/metadata.json
minsketch-0.1.dist-info/RECORD
minsketch-0.1.dist-info/top_level.txt
minsketch-0.1.dist-info/WHEEL
minsketch-0.1.dist-info/zip-safe
