Metadata-Version: 2.0
Name: minsketch
Version: 0.1
Summary: A flexible implementation of several min-sketch variants
Home-page: https://github.com/guydav/minsketch
Author: Guy Davidson
Author-email: guy@minerva.kgi.edu
License: MIT
Platform: UNKNOWN
